setup.py
sonicFlux/__init__.py
sonicFlux.egg-info/PKG-INFO
sonicFlux.egg-info/SOURCES.txt
sonicFlux.egg-info/dependency_links.txt
sonicFlux.egg-info/entry_points.txt
sonicFlux.egg-info/requires.txt
sonicFlux.egg-info/top_level.txt
sonicFlux.egg-info/zip-safe
sonicFlux/r1_4_1_dev/__init__.py
sonicFlux/r1_5/__init__.py
sonicFlux/r1_6/__init__.py
sonicFlux/r1_6_dev/__init__.py
sonicFlux/r2_0_0/__init__.py